card_metric_component/__init__.py
card_metric_component/example.py
card_metric_component/frontend/build/asset-manifest.json
card_metric_component/frontend/build/bootstrap.min.css
card_metric_component/frontend/build/bootstrap.min.css.map
card_metric_component/frontend/build/index.html
card_metric_component/frontend/build/static/css/main.9c19ff4b.css
card_metric_component/frontend/build/static/css/main.9c19ff4b.css.map
card_metric_component/frontend/build/static/js/main.6d7ec7b5.js
card_metric_component/frontend/build/static/js/main.6d7ec7b5.js.LICENSE.txt
card_metric_component/frontend/build/static/js/main.6d7ec7b5.js.map
custom_card_metric_component-0.0.4.dist-info/LICENSE
custom_card_metric_component-0.0.4.dist-info/METADATA
custom_card_metric_component-0.0.4.dist-info/WHEEL
custom_card_metric_component-0.0.4.dist-info/top_level.txt
custom_card_metric_component-0.0.4.dist-info/RECORD
